unpdf/__init__.py
unpdf/libpdf.cpython-311-aarch64-linux-gnu.so
unpdf/libpdf.pyx
unpdf/table.py
unpdf.libs/libpdfium-3c8f3197.so
unpdf-1.0.0.dist-info/METADATA
unpdf-1.0.0.dist-info/WHEEL
unpdf-1.0.0.dist-info/top_level.txt
unpdf-1.0.0.dist-info/RECORD
unpdf-1.0.0.dist-info/licenses/LICENSE
