Metadata-Version: 2.4
Name: unPDF
Version: 1.0.0
Summary: Quickly extract text characters and character metadata from pdfs using pdfium.
Author-email: Laurens Janssen <digi-deity@laurens.xyz>
License: Apache-2.0
Project-URL: Repository, https://github.com/digi-deity/unPDF
Requires-Python: >=3.9
License-File: LICENSE
Dynamic: license-file
